LICENSE.txt
README.md
setup.py
src/probotlib/__init__.py
src/probotlib.egg-info/PKG-INFO
src/probotlib.egg-info/SOURCES.txt
src/probotlib.egg-info/dependency_links.txt
src/probotlib.egg-info/top_level.txt