Metadata-Version: 2.2
Name: probotlib
Version: 1.4
Summary: A small library that helps verify credit transfers.
Home-page: https://github.com/Minegamer2024/probot.git
Author: Minegamer
Keywords: python,discord.py,discord,probotlib,probot discord,discord probot,bot,transfer
Classifier: Programming Language :: Python :: 3.8
Classifier: Programming Language :: Python :: 3.9
Classifier: Programming Language :: Python :: 3.10
Classifier: Programming Language :: Python :: 3.11
Classifier: Programming Language :: Python :: 3.12
Classifier: Operating System :: OS Independent
Classifier: License :: OSI Approved :: MIT License
Requires-Python: >=3.8,<=3.12.9
License-File: LICENSE.txt
Dynamic: author
Dynamic: classifier
Dynamic: description
Dynamic: description-content-type
Dynamic: home-page
Dynamic: keywords
Dynamic: requires-python
Dynamic: summary
